{
  "language": "Western Frisian",
  "iso639_3": "fry",
  "alphabetical": [
    "A",
    "B",
    "C",
    "D",
    "E",
    "F",
    "G",
    "H",
    "I",
    "J",
    "K",
    "L",
    "M",
    "N",
    "O",
    "P",
    "R",
    "S",
    "T",
    "U",
    "V",
    "W",
    "Z",
    "Y",
    "À",
    "Á",
    "Â",
    "Ä",
    "È",
    "É",
    "Ê",
    "Ë",
    "Í",
    "Ï",
    "Ó",
    "Ô",
    "Ö",
    "Ú",
    "Û",
    "Ü",
    "Ý"
  ],
  "uppercase": [
    "A",
    "B",
    "C",
    "D",
    "E",
    "F",
    "G",
    "H",
    "I",
    "J",
    "K",
    "L",
    "M",
    "N",
    "O",
    "P",
    "R",
    "S",
    "T",
    "U",
    "V",
    "W",
    "Z",
    "Y",
    "À",
    "Á",
    "Â",
    "Ä",
    "È",
    "É",
    "Ê",
    "Ë",
    "Í",
    "Ï",
    "Ó",
    "Ô",
    "Ö",
    "Ú",
    "Û",
    "Ü",
    "Ý"
  ],
  "lowercase": [
    "a",
    "b",
    "c",
    "d",
    "e",
    "f",
    "g",
    "h",
    "i",
    "j",
    "k",
    "l",
    "m",
    "n",
    "o",
    "p",
    "r",
    "s",
    "t",
    "u",
    "v",
    "w",
    "z",
    "y",
    "à",
    "á",
    "â",
    "ä",
    "è",
    "é",
    "ê",
    "ë",
    "í",
    "ï",
    "ó",
    "ô",
    "ö",
    "ú",
    "û",
    "ü",
    "ý"
  ],
  "frequency": {
    "a": 0.0779,
    "b": 0.0165,
    "c": 0.0094,
    "d": 0.0515,
    "e": 0.158,
    "f": 0.0268,
    "g": 0.0186,
    "h": 0.0197,
    "i": 0.0731,
    "j": 0.0142,
    "k": 0.0333,
    "l": 0.0375,
    "m": 0.0258,
    "n": 0.0981,
    "o": 0.045,
    "p": 0.0154,
    "r": 0.0713,
    "s": 0.0588,
    "t": 0.0686,
    "u": 0.0181,
    "v": 0.0036,
    "w": 0.0177,
    "z": 0.0036,
    "y": 0.0221,
    "à": 0.0,
    "á": 0.0,
    "â": 0.0039,
    "ä": 0.0,
    "è": 0.0,
    "é": 0.0001,
    "ê": 0.003,
    "ë": 0.0001,
    "í": 0.0,
    "ï": 0.0001,
    "ó": 0.0,
    "ô": 0.001,
    "ö": 0.0001,
    "ú": 0.0025,
    "û": 0.0043,
    "ü": 0.0001,
    "ý": 0.0
  },
  "script": "Latn",
  "iso639_1": "fy",
  "hello_how_are_you": "Hoi, hoe giet it mei dy?"
}