{
  "language": "Malagasy",
  "iso639_3": "mlg",
  "alphabetical": [
    "A",
    "B",
    "D",
    "E",
    "F",
    "G",
    "H",
    "I",
    "J",
    "K",
    "L",
    "M",
    "N",
    "O",
    "P",
    "R",
    "S",
    "T",
    "V",
    "Y",
    "Z",
    "À",
    "Â",
    "È",
    "É",
    "Ê",
    "Ë",
    "Ì",
    "Î",
    "Ï",
    "Ñ",
    "Ô"
  ],
  "uppercase": [
    "A",
    "B",
    "D",
    "E",
    "F",
    "G",
    "H",
    "I",
    "J",
    "K",
    "L",
    "M",
    "N",
    "O",
    "P",
    "R",
    "S",
    "T",
    "V",
    "Y",
    "Z",
    "À",
    "Â",
    "È",
    "É",
    "Ê",
    "Ë",
    "Ì",
    "Î",
    "Ï",
    "Ñ",
    "Ô"
  ],
  "lowercase": [
    "a",
    "b",
    "d",
    "e",
    "f",
    "g",
    "h",
    "i",
    "j",
    "k",
    "l",
    "m",
    "n",
    "o",
    "p",
    "r",
    "s",
    "t",
    "v",
    "y",
    "z",
    "à",
    "â",
    "è",
    "é",
    "ê",
    "ë",
    "ì",
    "î",
    "ï",
    "ñ",
    "ô"
  ],
  "frequency": {
    "a": 0.2165,
    "b": 0.0088,
    "d": 0.0406,
    "e": 0.0431,
    "f": 0.0154,
    "g": 0.0051,
    "h": 0.0195,
    "i": 0.1126,
    "j": 0.005,
    "k": 0.0201,
    "l": 0.0198,
    "m": 0.0421,
    "n": 0.1494,
    "o": 0.0698,
    "p": 0.0127,
    "r": 0.0583,
    "s": 0.0264,
    "t": 0.0454,
    "v": 0.0081,
    "y": 0.066,
    "z": 0.0087,
    "à": 0.0031,
    "â": 0.0001,
    "è": 0.0004,
    "é": 0.0011,
    "ê": 0.0,
    "ë": 0.0,
    "ì": 0.0,
    "î": 0.0,
    "ï": 0.0,
    "ñ": 0.0,
    "ô": 0.0018
  },
  "script": "Latn",
  "iso639_1": "mg",
  "hello_how_are_you": "Salama manao ahoana ny fahasalamanao?"
}