{
  "language": "Toba",
  "iso639_3": "tob",
  "alphabetical": [
    "A",
    "B",
    "C",
    "D",
    "E",
    "F",
    "G",
    "H",
    "I",
    "J",
    "K",
    "L",
    "M",
    "N",
    "O",
    "P",
    "Q",
    "R",
    "S",
    "T",
    "U",
    "V",
    "X",
    "Y",
    "Z",
    "Á",
    "Í",
    "Ñ",
    "Ó",
    "Ý",
    "Ÿ",
    "Ỹ"
  ],
  "uppercase": [
    "A",
    "B",
    "C",
    "D",
    "E",
    "F",
    "G",
    "H",
    "I",
    "J",
    "K",
    "L",
    "M",
    "N",
    "O",
    "P",
    "Q",
    "R",
    "S",
    "T",
    "U",
    "V",
    "X",
    "Y",
    "Z",
    "Á",
    "Í",
    "Ñ",
    "Ó",
    "Ý",
    "Ÿ",
    "Ỹ"
  ],
  "lowercase": [
    "a",
    "b",
    "c",
    "d",
    "e",
    "f",
    "g",
    "h",
    "i",
    "j",
    "k",
    "l",
    "m",
    "n",
    "o",
    "p",
    "q",
    "r",
    "s",
    "t",
    "u",
    "v",
    "x",
    "y",
    "z",
    "á",
    "í",
    "ñ",
    "ó",
    "ý",
    "ÿ",
    "ỹ"
  ],
  "frequency": {
    "d": 0.007,
    "a": 0.2388,
    "n": 0.0623,
    "c": 0.0517,
    "h": 0.0311,
    "e": 0.0779,
    "r": 0.0073,
    "o": 0.0618,
    "u": 0.0493,
    "s": 0.028,
    "q": 0.0474,
    "t": 0.0603,
    "l": 0.0387,
    "i": 0.0892,
    "m": 0.022,
    "ý": 0.0083,
    "y": 0.0093,
    "x": 0.0422,
    "g": 0.0225,
    "j": 0.0018,
    "ñ": 0.0139,
    "p": 0.023,
    "v": 0.0038,
    "b": 0.0005,
    "z": 0.0003,
    "ÿ": 0.0003,
    "f": 0.0002,
    "í": 0.0002,
    "ó": 0.0002,
    "ỹ": 0.0003,
    "k": 0.0002,
    "á": 0.0002
  },
  "script": "Latn",
  "digits": [
    "0",
    "1",
    "2",
    "3",
    "4",
    "5",
    "6",
    "7",
    "8",
    "9"
  ],
  "iso639_1": null
}